{"args":["s:character-female-e2",{"args":["sn:PhysicsBody",{"args":["s:body_id",{"type":"RID"},"s:shape",{"type":"RID"},"s:transform",{"args":[1.0,0.0,0.0,0.0,1.0,0.0,0.0,0.0,1.0,0.0,0.0,0.0],"type":"Transform3D"},"s:shape_ref","s:","s:shape_position",{"args":[0.0,0.0,0.0],"type":"Vector3"},"s:axis_lock_linear_x",false,"s:axis_lock_linear_y",false,"s:axis_lock_linear_z",false,"s:axis_lock_angular_x",true,"s:axis_lock_angular_y",true,"s:axis_lock_angular_z",true,"s:continous_collision_detection",true],"type":"Dictionary"},"sn:Movement",{"args":["s:direction",{"args":[0.0,0.0,0.0],"type":"Vector3"},"s:speed","f:20.0","s:speed_mod_factor","f:1.0","s:jump_force","f:10.0","s:last_jump_input_time","f:0.0","s:bounce_force","f:1.0","s:state","i:1"],"type":"Dictionary"},"sn:Controller",{"args":["s:forward_key","sn:move_up_p1","s:backward_key","sn:move_down_p1","s:right_key","sn:move_right_p1","s:left_key","sn:move_left_p1","s:rs_up","sn:rs_up_p1","s:rs_down","sn:rs_down_p1","s:rs_left","sn:rs_left_p1","s:rs_right","sn:rs_right_p1","s:horizontal_axis","sn:","s:vertical_axis","sn:","s:jump_key","sn:jump_p1","s:dash_key","sn:dash_p1","s:hit_key","sn:hit_p1","s:throw_action","sn:throw_p1"],"type":"Dictionary"},"sn:Player",{"args":[],"type":"Dictionary"},"sn:Dash",{"args":["s:max_distance","f:10.0","s:speed","f:30.0","s:direction",{"args":[0.0,0.0,0.0],"type":"Vector3"},"s:curr_dashing_time","f:0.0","s:cooldown_time","f:0.0"],"type":"Dictionary"}],"type":"Dictionary"}],"type":"Dictionary"}